elmer_circuitbuilder.py
elmer_circuitbuilder-1.0.5.dist-info/AUTHORS.rst
elmer_circuitbuilder-1.0.5.dist-info/LICENSE
elmer_circuitbuilder-1.0.5.dist-info/METADATA
elmer_circuitbuilder-1.0.5.dist-info/WHEEL
elmer_circuitbuilder-1.0.5.dist-info/top_level.txt
elmer_circuitbuilder-1.0.5.dist-info/RECORD
