Metadata-Version: 2.1
Name: elmer_circuitbuilder
Version: 1.0.5
Summary: Python module for creating the circuit simulation definitions for Elmer FEM. The circuit definitions enable easy setup of coils (e.g. massive, stranded, and foil) in 2D and 3D for magnetodynamics applications.
Home-page: https://github.com/ElmerCSC/elmer_circuitbuilder.git
Author: Jonathan Velasco
Author-email: velasco_jonathan@hotmail.com
Maintainer: CSC - IT Center for Science :  ElmerFEM Developers
License: GNU Lesser General Public License v3
Keywords: elmer_circuitbuilder
Classifier: Development Status :: 5 - Production/Stable
Classifier: Intended Audience :: Developers
Classifier: License :: OSI Approved :: GNU Lesser General Public License v3 (LGPLv3)
Classifier: Natural Language :: English
Classifier: Programming Language :: Python :: 3
Classifier: Programming Language :: Python :: 3.7
Classifier: Programming Language :: Python :: 3.8
Classifier: Programming Language :: Python :: 3.9
Requires-Python: >=3.7
License-File: LICENSE
License-File: AUTHORS.rst
Provides-Extra: dev
Requires-Dist: pytest >=3.7 ; extra == 'dev'
